investimentos/__init__.py
investimentos/investimentos.py
meu_investimento_ferrufato-0.2.dist-info/licenses/LICENSE
meu_investimento_ferrufato-0.2.dist-info/METADATA
meu_investimento_ferrufato-0.2.dist-info/WHEEL
meu_investimento_ferrufato-0.2.dist-info/top_level.txt
meu_investimento_ferrufato-0.2.dist-info/RECORD
